nitor_vault-2.7.0.dist-info/METADATA
nitor_vault-2.7.0.dist-info/WHEEL
nitor_vault-2.7.0.dist-info/entry_points.txt
n_vault.libs/libgcc_s-1e52349c.so.1
n_vault/nitor_vault_rs.pyi
n_vault/py.typed
n_vault/__init__.py
n_vault/cli.py
n_vault/vault.py
n_vault/nitor_vault_rs.cpython-313t-x86_64-linux-musl.so
nitor_vault-2.7.0.dist-info/RECORD
