Metadata-Version: 2.4
Name: nitor-vault
Version: 2.7.0
Classifier: Programming Language :: Rust
Classifier: Programming Language :: Python :: Implementation :: CPython
Requires-Dist: maturin ; extra == 'build'
Requires-Dist: wheel ; extra == 'build'
Requires-Dist: maturin ; extra == 'dev'
Requires-Dist: ruff ; extra == 'dev'
Provides-Extra: build
Provides-Extra: dev
Summary: Vault for storing locally encrypted data in S3 using KMS keys
Author-email: Pasi Niemi <pasi@nitor.com>, Akseli Lukkarila <akseli.lukkarila@nitor.com>
License: Apache-2.0
Requires-Python: >=3.9
Project-URL: Repository, https://github.com/NitorCreations/vault
Project-URL: Homepage, https://github.com/NitorCreations/vault
